odoo/addons/sale_viewer/__init__.py
odoo/addons/sale_viewer/__manifest__.py
odoo/addons/sale_viewer/security/ir.model.access.csv
odoo/addons/sale_viewer/security/sale_security.xml
odoo/addons/sale_viewer/static/description/icon.png
odoo/addons/sale_viewer/views/partner.xml
odoo/addons/sale_viewer/views/product.xml
odoo/addons/sale_viewer/views/sale.xml
odoo12_addon_sale_viewer-12.0.1.0.0.99.dev2.dist-info/METADATA
odoo12_addon_sale_viewer-12.0.1.0.0.99.dev2.dist-info/WHEEL
odoo12_addon_sale_viewer-12.0.1.0.0.99.dev2.dist-info/top_level.txt
odoo12_addon_sale_viewer-12.0.1.0.0.99.dev2.dist-info/RECORD
